{"lukevers":{"master":true,"mode":"+o","host":"~lukevers@dylwhich.xen.prgmr.com"},"DuoNoxSol":{"mode":"+o","host":"~duonoxsol@dylwhich.xen.prgmr.com"},"Dan68":{"mode":"+o","host":"~Dan@dude.meshwith.me"},"derpz":{"mode":"+o","host":"~derp@2600:3c01::f03c:91ff:fedf:a466"},"thefinn93":{"mode":"+o","host":"~thefinn93@thefinn93.com"},"dylwhich":{"mode":"+v","host":"~dylwhich@dylwhich.xen.prgmr.com"},"inhies":{"mode":"+v","host":"~inhies@cpe-76-88-147-181.hawaii.res.rr.com"},"snap1":{"mode":"+v","host":"~snap@snap.xen.prgmr.com"},"werecat":{"user":{"mode":"+o","host":"werecat@undefined"}}}